mackup/__init__.py
mackup/application.py
mackup/appsdb.py
mackup/config.py
mackup/constants.py
mackup/mackup.py
mackup/main.py
mackup/utils.py
mackup/applications/1password-4.cfg
mackup/applications/2do.cfg
mackup/applications/ack.cfg
mackup/applications/act.cfg
mackup/applications/activitywatch.cfg
mackup/applications/adium.cfg
mackup/applications/adobe-camera-raw.cfg
mackup/applications/aerc.cfg
mackup/applications/aerospace.cfg
mackup/applications/affinity-designer.cfg
mackup/applications/affinity-photo.cfg
mackup/applications/affinity-publisher.cfg
mackup/applications/airflow.cfg
mackup/applications/airmail.cfg
mackup/applications/akamai-cli.cfg
mackup/applications/alacritty.cfg
mackup/applications/aldente.cfg
mackup/applications/alt-tab.cfg
mackup/applications/amethyst.cfg
mackup/applications/ancient-domains-of-mystery.cfg
mackup/applications/androidstudio-13.cfg
mackup/applications/ansible.cfg
mackup/applications/appcleaner.cfg
mackup/applications/appcode-2.cfg
mackup/applications/appcode-3.cfg
mackup/applications/appcode-31.cfg
mackup/applications/appcode-32.cfg
mackup/applications/apple-music.cfg
mackup/applications/apptivate.cfg
mackup/applications/arara.cfg
mackup/applications/aria2c.cfg
mackup/applications/arm.cfg
mackup/applications/asciinema.cfg
mackup/applications/asdf.cfg
mackup/applications/aspell.cfg
mackup/applications/astyle.cfg
mackup/applications/atlantis.cfg
mackup/applications/atom.cfg
mackup/applications/audacious.cfg
mackup/applications/auskey.cfg
mackup/applications/autokey.cfg
mackup/applications/awareness.cfg
mackup/applications/aws.cfg
mackup/applications/azure.cfg
mackup/applications/b-ryan_powerline-shell.cfg
mackup/applications/bartender.cfg
mackup/applications/base.cfg
mackup/applications/bash-it.cfg
mackup/applications/bash.cfg
mackup/applications/bat.cfg
mackup/applications/bc.cfg
mackup/applications/beatport-pro.cfg
mackup/applications/beets.cfg
mackup/applications/bettersnaptool.cfg
mackup/applications/bettertouchtool.cfg
mackup-0.10.0.dist-info/METADATA
mackup-0.10.0.dist-info/WHEEL
mackup-0.10.0.dist-info/entry_points.txt
mackup-0.10.0.dist-info/licenses/LICENSE
mackup-0.10.0.dist-info/RECORD
