Metadata-Version: 2.4
Name: mackup
Version: 0.10.0
Summary: Backup and keep your application settings in sync.
Project-URL: Repository, https://github.com/lra/mackup.git
Project-URL: Issues, https://github.com/lra/mackup/issues
Project-URL: Changelog, https://github.com/lra/mackup/releases
Author-email: Laurent Raufaste <analogue@glop.org>
License-Expression: GPL-3.0-or-later
License-File: LICENSE
Classifier: Development Status :: 5 - Production/Stable
Classifier: Environment :: Console
Classifier: Intended Audience :: Developers
Classifier: Intended Audience :: System Administrators
Classifier: License :: OSI Approved :: GNU General Public License v3 or later (GPLv3+)
Classifier: Operating System :: MacOS :: MacOS X
Classifier: Operating System :: POSIX :: Linux
Classifier: Programming Language :: Python :: 3
Classifier: Programming Language :: Python :: 3 :: Only
Classifier: Programming Language :: Python :: 3.9
Classifier: Programming Language :: Python :: 3.10
Classifier: Programming Language :: Python :: 3.11
Classifier: Programming Language :: Python :: 3.12
Classifier: Programming Language :: Python :: 3.13
Classifier: Programming Language :: Python :: 3.14
Classifier: Topic :: System :: Archiving :: Backup
Classifier: Topic :: Utilities
Requires-Python: >=3.9
Requires-Dist: docopt-ng>=0.9.0
